rda_python_dsrqst/PgRDARqst.py
rda_python_dsrqst/PgRqst.py
rda_python_dsrqst/PgSubset.py
rda_python_dsrqst/__init__.py
rda_python_dsrqst/ds_rqst.py
rda_python_dsrqst/dsrqst.py
rda_python_dsrqst/dsrqst.usg
rda_python_dsrqst/pg_rdarqst.py
rda_python_dsrqst/pg_rqst.py
rda_python_dsrqst/pg_subset.py
rda_python_dsrqst-2.0.0.dist-info/licenses/LICENSE
rda_python_dsrqst-2.0.0.dist-info/METADATA
rda_python_dsrqst-2.0.0.dist-info/WHEEL
rda_python_dsrqst-2.0.0.dist-info/entry_points.txt
rda_python_dsrqst-2.0.0.dist-info/top_level.txt
rda_python_dsrqst-2.0.0.dist-info/RECORD
